geeda/__init__.py
geeda/column/__init__.py
geeda/column/auto_binning.py
geeda/column/check_distribution.py
geeda/column/check_duplicates.py
geeda/column/check_inf.py
geeda/column/check_nan.py
geeda/column/is_categorical.py
geeda/column/is_pseudo_categorical.py
geeda/dataframe/__init__.py
geeda/dataframe/check_duplicates.py
geeda/dataframe/geeda.py
geeda/dataframe/print_special_values_report.py
geeda/printout.py
geeda/utils.py
geeda-0.1.0.dist-info/LICENSE
geeda-0.1.0.dist-info/WHEEL
geeda-0.1.0.dist-info/METADATA
geeda-0.1.0.dist-info/RECORD
