Metadata-Version: 2.1
Name: geeda
Version: 0.1.0
Summary: General EDA Framework for Pandas DataFrames
License: LICENSE
Author: Jason Zhang
Author-email: jasonjzhang17@gmail.com
Requires-Python: >=3.8,<3.12
Classifier: License :: OSI Approved :: MIT License
Classifier: License :: Other/Proprietary License
Classifier: Operating System :: OS Independent
Classifier: Programming Language :: Python :: 3
Classifier: Programming Language :: Python :: 3.8
Classifier: Programming Language :: Python :: 3.9
Classifier: Programming Language :: Python :: 3.10
Classifier: Programming Language :: Python :: 3.11
Classifier: Programming Language :: Python :: 3
Requires-Dist: ipykernel (>=6.15.2,<7.0.0)
Requires-Dist: pandas (>=1.4.3,<2.0.0)
Requires-Dist: pre-commit (>=2.20.0,<3.0.0)
Requires-Dist: scipy (>=1.9.1,<2.0.0)
Requires-Dist: tabulate (>=0.8.10,<0.9.0)
